PyCO2SYS/__init__.py
PyCO2SYS/bio.py
PyCO2SYS/constants.py
PyCO2SYS/convert.py
PyCO2SYS/gas.py
PyCO2SYS/meta.py
PyCO2SYS/minimal.py
PyCO2SYS/original.py
PyCO2SYS/salts.py
PyCO2SYS/solubility.py
PyCO2SYS/uncertainty.py
PyCO2SYS/upsilon.py
PyCO2SYS/api/__init__.py
PyCO2SYS/api/ezio/__init__.py
PyCO2SYS/api/ezio/ezio_utils.py
PyCO2SYS/buffers/__init__.py
PyCO2SYS/buffers/explicit.py
PyCO2SYS/engine/__init__.py
PyCO2SYS/engine/nd.py
PyCO2SYS/equilibria/__init__.py
PyCO2SYS/equilibria/p1atm.py
PyCO2SYS/equilibria/pcx.py
PyCO2SYS/equilibria/pressured.py
PyCO2SYS/solve/__init__.py
PyCO2SYS/solve/delta.py
PyCO2SYS/solve/get.py
PyCO2SYS/solve/initialise.py
PyCO2SYS-1.8.3.4.dist-info/LICENSE
PyCO2SYS-1.8.3.4.dist-info/METADATA
PyCO2SYS-1.8.3.4.dist-info/WHEEL
PyCO2SYS-1.8.3.4.dist-info/top_level.txt
PyCO2SYS-1.8.3.4.dist-info/RECORD
