Metadata-Version: 2.1
Name: PyCO2SYS
Version: 1.8.3.4
Summary: PyCO2SYS: marine carbonate system calculations in Python
Classifier: Development Status :: 5 - Production/Stable
Classifier: Programming Language :: Python :: 3.7
Classifier: Programming Language :: Python :: 3.8
Classifier: Programming Language :: Python :: 3.9
Classifier: Programming Language :: Python :: 3.10
Classifier: Programming Language :: Python :: 3.11
Classifier: Programming Language :: Python :: 3.12
Classifier: License :: OSI Approved :: GNU General Public License v3 (GPLv3)
Classifier: Operating System :: OS Independent
Classifier: Natural Language :: English
Classifier: Intended Audience :: Science/Research
Classifier: Topic :: Scientific/Engineering :: Chemistry
Classifier: Topic :: Scientific/Engineering :: Oceanography
License-File: LICENSE
Requires-Dist: autograd
Requires-Dist: numpy
